dwave/preprocessing/cyfix_variables.cp39-win_amd64.pyd
dwave/preprocessing/cyfix_variables.cpp
dwave/preprocessing/cyfix_variables.pyx
dwave/preprocessing/libcpp.pxd
dwave/preprocessing/lower_bounds.py
dwave/preprocessing/__init__.py
dwave/preprocessing/composites/clip.py
dwave/preprocessing/composites/connected_components.py
dwave/preprocessing/composites/fix_variables.py
dwave/preprocessing/composites/scale.py
dwave/preprocessing/composites/spin_reversal_transform.py
dwave/preprocessing/composites/__init__.py
dwave/preprocessing/include/dwave/exceptions.hpp
dwave/preprocessing/include/dwave/flags.hpp
dwave/preprocessing/include/dwave/presolve.hpp
dwave/preprocessing/include/dwave-preprocessing/fix_variables.hpp
dwave/preprocessing/include/dwave-preprocessing/helper_data_structures.hpp
dwave/preprocessing/include/dwave-preprocessing/helper_graph_algorithms.hpp
dwave/preprocessing/include/dwave-preprocessing/implication_network.hpp
dwave/preprocessing/include/dwave-preprocessing/mapping_policy.hpp
dwave/preprocessing/include/dwave-preprocessing/posiform_info.hpp
dwave/preprocessing/include/dwave-preprocessing/push_relabel.hpp
dwave/preprocessing/presolve/cypresolve.cp39-win_amd64.pyd
dwave/preprocessing/presolve/cypresolve.cpp
dwave/preprocessing/presolve/cypresolve.pxd
dwave/preprocessing/presolve/cypresolve.pyi
dwave/preprocessing/presolve/cypresolve.pyx
dwave/preprocessing/presolve/exceptions.py
dwave/preprocessing/presolve/pypresolve.py
dwave/preprocessing/presolve/__init__.pxd
dwave/preprocessing/presolve/__init__.py
dwave/preprocessing/src/exceptions.cpp
dwave/preprocessing/src/presolve.cpp
dwave/preprocessing/src/presolveimpl.hpp
dwave_preprocessing-0.6.10.dist-info/DELVEWHEEL
dwave_preprocessing-0.6.10.dist-info/METADATA
dwave_preprocessing-0.6.10.dist-info/RECORD
dwave_preprocessing-0.6.10.dist-info/top_level.txt
dwave_preprocessing-0.6.10.dist-info/WHEEL
dwave_preprocessing-0.6.10.dist-info/licenses/LICENSE
dwave_preprocessing.libs/.load-order-dwave_preprocessing-0.6.10
dwave_preprocessing.libs/msvcp140-9057d39b36b6c7d054865ee2bf9cde7a.dll
