Metadata-Version: 2.4
Name: dwave-preprocessing
Version: 0.6.10
Summary: An API for preprocessing tools
Home-page: https://github.com/dwavesystems/dwave-preprocessing
Download-URL: https://github.com/dwavesystems/dwave-preprocessing/releases
Author: D-Wave Systems Inc.
Author-email: tools@dwavesys.com
License: Apache 2.0
Classifier: License :: OSI Approved :: Apache Software License
Classifier: Operating System :: Microsoft :: Windows
Classifier: Operating System :: POSIX
Classifier: Operating System :: Unix
Classifier: Operating System :: MacOS
Classifier: Programming Language :: Python :: Implementation :: CPython
Classifier: Programming Language :: Python :: 3 :: Only
Classifier: Programming Language :: Python :: 3.9
Classifier: Programming Language :: Python :: 3.10
Classifier: Programming Language :: Python :: 3.11
Classifier: Programming Language :: Python :: 3.12
Classifier: Programming Language :: Python :: 3.13
Requires-Python: >=3.9
License-File: LICENSE
Requires-Dist: numpy<3.0.0,>=1.17.3
Requires-Dist: dimod<0.13.0,>=0.12.20
Dynamic: download-url
Dynamic: license-file
Dynamic: requires-dist
